LICENSE
MANIFEST.in
README.md
requirements.txt
setup.cfg
setup.py
versioneer.py
dfviz/__init__.py
dfviz/_version.py
dfviz/example.py
dfviz/fields.py
dfviz/sigslot.py
dfviz/utils.py
dfviz/widget.py
dfviz.egg-info/PKG-INFO
dfviz.egg-info/SOURCES.txt
dfviz.egg-info/dependency_links.txt
dfviz.egg-info/not-zip-safe
dfviz.egg-info/requires.txt
dfviz.egg-info/top_level.txt